VerityPy/__init__.py
VerityPy/processing/__init__.py
VerityPy/processing/analyzequality.py
VerityPy/processing/datefuncs.py
VerityPy/processing/exectransform.py
VerityPy/processing/field.py
VerityPy/processing/numfuncs.py
VerityPy/processing/qualityanalysis.py
VerityPy/processing/recfuncs.py
VerityPy/processing/refinedata.py
VerityPy/processing/remediateparsing.py
VerityPy/transforms/__init__.py
VerityPy/transforms/lookup.py
VerityPy/transforms/optypes.py
VerityPy/transforms/transform.py
VerityPy/utils/__init__.py
VerityPy/utils/reportfuncs.py
VerityPy-2024.1.21.dist-info/LICENSE
VerityPy-2024.1.21.dist-info/METADATA
VerityPy-2024.1.21.dist-info/WHEEL
VerityPy-2024.1.21.dist-info/top_level.txt
VerityPy-2024.1.21.dist-info/RECORD
