Metadata-Version: 2.1
Name: VerityPy
Version: 2024.1.21
Summary: VerityPy is a library by Technik Interlytics for Better Data = Better Decisions. It is a Data Inspector, Remediator, Normalizer on large structured data sets. It combines curated human expert knowledge gained from in-depth forensic analysis and remediating data in many fields, with Machine Learning pattern extraction results to know where to look, what to look for, and what to do about problems found lurking deep within huge data sets.
Author-email: Geoffrey Malafsky <gmalafsky@technikinterlytics.com>
License: License
Project-URL: Homepage, https://technikinterlytics.com
Project-URL: Documentation, https://technikinterlytics.com/VerityPy/
Keywords: data quality,data profiling,data enrichment,data normalization,data remediation,human data expert,data intelligence,embedded delimiter,data cleaning,data veracity,data prep,data wrangling,data forensics,data remediation,data science,data blending,structured data,metadata,broken records,parsing error
Classifier: Programming Language :: Python :: 3
Classifier: License :: Free for non-commercial use
Classifier: Topic :: Software Development :: Libraries :: Python Modules
Requires-Python: >=3.8
License-File: LICENSE
